MANIFEST.in
README.md
humanfuture.py
setup.py
HumanFuture.egg-info/PKG-INFO
HumanFuture.egg-info/SOURCES.txt
HumanFuture.egg-info/dependency_links.txt
HumanFuture.egg-info/top_level.txt