Metadata-Version: 1.0
Name: HumanFuture
Version: 0.2
Summary: Convert a future date to a human-friendly english format
Home-page: https://github.com/uniphil/HumanFuture
Author: Philip Schleihauf and Jamie Macdonald
Author-email: uniphil@gmail.com
License: GPLv3
Platform: UNKNOWN
